mungo/__init__.py
mungo/base.py
mungo/cli.py
mungo/repodata.py
mungo/solver.py
mungo-0.1.2.dist-info/LICENSE
mungo-0.1.2.dist-info/METADATA
mungo-0.1.2.dist-info/WHEEL
mungo-0.1.2.dist-info/entry_points.txt
mungo-0.1.2.dist-info/top_level.txt
mungo-0.1.2.dist-info/RECORD
