Metadata-Version: 2.1
Name: mungo
Version: 0.1.2
Summary: Quick environment solver
Home-page: https://github.com/christopher-schroeder/mungo
Author: Christopher Schröder, Till Hartmann
Author-email: christopher.schroeder@uni-due.de, till.hartmann@udo.edu
License: UNKNOWN
Platform: UNKNOWN
Classifier: Programming Language :: Python :: 3
Classifier: License :: OSI Approved :: MIT License
Classifier: Operating System :: Unix
Requires-Dist: pulp
Requires-Dist: packaging
Requires-Dist: pyyaml
Requires-Dist: joblib
Requires-Dist: graphviz
